openplzapi/__init__.py
openplzapi/api_base_client.py
openplzapi/api_client_factory.py
openplzapi/pagination.py
openplzapi/problem_details.py
openplzapi/at/__init__.py
openplzapi/at/api_client.py
openplzapi/at/district.py
openplzapi/at/district_summary.py
openplzapi/at/federal_province.py
openplzapi/at/federal_province_summary.py
openplzapi/at/locality.py
openplzapi/at/municipality.py
openplzapi/at/municipality_summary.py
openplzapi/at/street.py
openplzapi/ch/__init__.py
openplzapi/ch/api_client.py
openplzapi/ch/canton.py
openplzapi/ch/canton_summary.py
openplzapi/ch/commune.py
openplzapi/ch/commune_summary.py
openplzapi/ch/district.py
openplzapi/ch/district_summary.py
openplzapi/ch/locality.py
openplzapi/ch/street.py
openplzapi/de/__init__.py
openplzapi/de/api_client.py
openplzapi/de/district.py
openplzapi/de/district_summary.py
openplzapi/de/federal_state.py
openplzapi/de/federal_state_summary.py
openplzapi/de/government_region.py
openplzapi/de/government_region_summary.py
openplzapi/de/locality.py
openplzapi/de/municipal_association.py
openplzapi/de/municipal_association_summary.py
openplzapi/de/municipality.py
openplzapi/de/municipality_summary.py
openplzapi/de/street.py
openplzapi/li/__init__.py
openplzapi/li/api_client.py
openplzapi/li/commune.py
openplzapi/li/commune_summary.py
openplzapi/li/locality.py
openplzapi/li/street.py
openplzapi_client-0.1.2.dist-info/LICENSE
openplzapi_client-0.1.2.dist-info/METADATA
openplzapi_client-0.1.2.dist-info/WHEEL
openplzapi_client-0.1.2.dist-info/top_level.txt
openplzapi_client-0.1.2.dist-info/RECORD
