Metadata-Version: 2.2
Name: openplzapi-client
Version: 0.1.2
Summary: A client library for the OpenPLZ API project
Author-email: STÜBER SYSTEMS GmbH <opensource@stueber.de>
Project-URL: Repository, https://github.com/openpotato/openplzapi-client.py.git
Project-URL: Issues, https://github.com/openpotato/openplzapi-client.py/issues
Keywords: plz,postleitzahlen,postal codes,Strassenverzeichnis,street directory
Classifier: Development Status :: 4 - Beta
Classifier: Environment :: Console
Classifier: Environment :: Web Environment
Classifier: Framework :: AsyncIO
Classifier: Intended Audience :: Developers
Classifier: License :: OSI Approved :: MIT License
Classifier: Operating System :: OS Independent
Classifier: Programming Language :: Python :: 3 :: Only
Classifier: Programming Language :: Python :: 3.8
Classifier: Programming Language :: Python :: 3.9
Classifier: Programming Language :: Python :: 3.10
Classifier: Programming Language :: Python :: 3.11
Classifier: Programming Language :: Python :: 3.12
Classifier: Programming Language :: Python :: 3.13
Classifier: Topic :: Internet
Classifier: Topic :: Internet :: WWW/HTTP
Classifier: Topic :: Software Development
Classifier: Topic :: Software Development :: Libraries
Classifier: Topic :: Software Development :: Libraries :: Python Modules
Requires-Python: >=3.8
License-File: LICENSE
Requires-Dist: requests>=2.32.3
